BacAnt/__init__.py
BacAnt/bacant.py
BacAnt/html_data.py
BacAnt/Integron_Finder/__init__.py
BacAnt/Integron_Finder/integron_finder/__init__.py
BacAnt/Integron_Finder/integron_finder/annotation.py
BacAnt/Integron_Finder/integron_finder/attc.py
BacAnt/Integron_Finder/integron_finder/config.py
BacAnt/Integron_Finder/integron_finder/hmm.py
BacAnt/Integron_Finder/integron_finder/infernal.py
BacAnt/Integron_Finder/integron_finder/integrase.py
BacAnt/Integron_Finder/integron_finder/integron.py
BacAnt/Integron_Finder/integron_finder/prot_db.py
BacAnt/Integron_Finder/integron_finder/results.py
BacAnt/Integron_Finder/integron_finder/topology.py
BacAnt/Integron_Finder/integron_finder/utils.py
BacAnt/Integron_Finder/scripts/__init__.py
BacAnt/Integron_Finder/scripts/finder.py
BacAnt-3.4.0.data/data/BacAnt/IntegronDB/Integron.fasta
BacAnt-3.4.0.data/data/BacAnt/IntegronDB/Integron.nhr
BacAnt-3.4.0.data/data/BacAnt/IntegronDB/Integron.nin
BacAnt-3.4.0.data/data/BacAnt/IntegronDB/Integron.nsq
BacAnt-3.4.0.data/data/BacAnt/Integron_Finder/data/Functional_annotation/Resfams.hmm
BacAnt-3.4.0.data/data/BacAnt/Integron_Finder/data/Models/attc_4.cm
BacAnt-3.4.0.data/data/BacAnt/Integron_Finder/data/Models/integron_integrase.hmm
BacAnt-3.4.0.data/data/BacAnt/Integron_Finder/data/Models/phage-int.hmm
BacAnt-3.4.0.data/data/BacAnt/Integron_Finder/data/Models/variants_Pc_intI1.fst
BacAnt-3.4.0.data/data/BacAnt/Integron_Finder/data/Replicons/Data-Test-IFv2.tar.gz
BacAnt-3.4.0.data/data/BacAnt/Integron_Finder/data/Replicons/Gembase/Genes/ACBA.0917.00019.gen
BacAnt-3.4.0.data/data/BacAnt/Integron_Finder/data/Replicons/Gembase/Genes/ESCO001.C.00001.C001.gen
BacAnt-3.4.0.data/data/BacAnt/Integron_Finder/data/Replicons/Gembase/Genes/KLPN.1017.00001.gen
BacAnt-3.4.0.data/data/BacAnt/Integron_Finder/data/Replicons/Gembase/Genes/KLPN.1017.01652.gen
BacAnt-3.4.0.data/data/BacAnt/Integron_Finder/data/Replicons/Gembase/LSTINFO/ACBA.0917.00019.lst
BacAnt-3.4.0.dist-info/LICENSE
BacAnt-3.4.0.dist-info/METADATA
BacAnt-3.4.0.dist-info/WHEEL
BacAnt-3.4.0.dist-info/entry_points.txt
BacAnt-3.4.0.dist-info/top_level.txt
BacAnt-3.4.0.dist-info/RECORD
