Metadata-Version: 2.1
Name: BacAnt
Version: 3.4.0
Summary: This program is designed for annotation of antimicrobal resistance(AMR), transposon(Tn) and integron(In) in bacteria
Home-page: https://github.com/xthua/bacant.git
Author: Hong Wenjie
Author-email: hwj1061@tkgeneclub.con
License: UNKNOWN
Platform: linux
Classifier: Development Status :: 5 - Production/Stable
Classifier: Environment :: Console
Classifier: Operating System :: POSIX
Classifier: Programming Language :: Python :: 3
Classifier: Programming Language :: Python :: 3.5
Classifier: Programming Language :: Python :: 3.6
Classifier: Programming Language :: Python :: 3.7
Classifier: License :: OSI Approved :: GNU General Public License v3 (GPLv3)
Classifier: Intended Audience :: Science/Research
Classifier: Topic :: Scientific/Engineering :: Bio-Informatics
Requires-Dist: biopython (==1.76)
Requires-Dist: matplotlib (==3.1.3)
Requires-Dist: numpy (==1.19.0)
Requires-Dist: bcbio-gff (==0.6.6)
Requires-Dist: colorlog (==4.2.1)
Requires-Dist: pandas (==0.25.1)
Requires-Dist: reportlab (==3.5.32)
